{"type":"PR","pr":{"number":56,"head":"5f6a0e224f49eef6bab54271a0fef33fd40c623d"},"user":"rajat","status":"pending_publish","branch":"cms/2020-07-03-how-to-become-an-artist-1","collection":"blogs","title":"Become An Artist And Jumpstart Your Art Career In 6 Steps","description":"It's never too late nor too early to start making art. In fact, becoming an artist is a very achievable goal. If you have always dreamt of pursuing art as a career option, here are 6 steps that will help you start the journey.\n","objects":{"entry":{"path":"src/pages/blog/2020-07-03-how-to-become-an-artist-1.md","sha":"c186be9c642b888b869a7d707ad4106c9c172ee3"},"files":[]},"timeStamp":"2020-07-03T11:55:17.053Z"}